design.sv
// Code your design here
module adder_hw4(in1,in2,in3,in4,out,enbl,clk,rst);
  input [7:0] in1,in2,in3,in4;
  input [1:0] enbl;
  input clk,rst;
  output reg [7:0] out;
  
  wire [7:0] out1,out2,sum;
  reg [7:0] a,b,c,d,sum1,sum2;

  always@(posedge clk or negedge rst)begin
    if(rst)begin
      a<=0;b<=0;c<=0;d<=0;
      out<=0;sum1<=0;sum2<=0;
    end
    else begin
      out<= sum;
      if(enbl==0)begin
        a<=in1;
        b<=in2;
      end
      if(enbl==1)begin
        c<=in3;
        sum1<=out1;
      end
      if(enbl==2)begin
        d<=in4;
        sum2<=out2;
      end
    end
  end
  
  assign out1 = a+b;
  assign out2 = c+sum1;
  assign sum = d+ sum2;
  

endmodule

testbench.sv

module adder_hw4_tb();
  reg [7:0] in1,in2,in3,in4;
  reg [1:0] enbl;
  reg clk,rst;
  wire [7:0] out;
  
  adder_hw4 uut(.clk(clk),
                .enbl(enbl),
                .in1(in1),
                .in2(in2),
                .in3(in3),
                .in4(in4),
                .rst(rst),
                .out(out));
  
   initial begin
    clk = 0;
    forever #10 clk = ~clk;
  end
  
  initial begin
    rst <=1;
    
    $monitor("%d Values Reset=%d Enable=%d A=%d B=%d C=%d E=%d Sum=%d",$time,rst,enbl,in1,in2,in3,in4,out);
    
    #20
    rst <=0;
    enbl <= 0;
    in1  <= 2;
    in2 <= 3;
    in3  <= 4;
    in4 <= 5;
    #20
    enbl  <= 1;
    #20
    enbl  <= 2;
    #200 $finish;  
  end
  
  initial begin
    $dumpfile("dump.vcd"); 
    $dumpvars;
end
 
endmodule

dump.vcd
$date
	Tue Dec 17 01:55:10 2019
$end

$version
	Synopsys VCS version P-2019.06-1
$end

$timescale
	1ns
$end

$comment Csum: 1 8538942f03b594c2 $end


$scope module adder_hw4_tb $end
$var reg 8 ! in1 [7:0] $end
$var reg 8 " in2 [7:0] $end
$var reg 8 # in3 [7:0] $end
$var reg 8 $ in4 [7:0] $end
$var reg 2 % enbl [1:0] $end
$var reg 1 & clk $end
$var reg 1 ' rst $end
$var wire 8 ( out [7:0] $end

$scope module uut $end
$var wire 8 ! in1 [7:0] $end
$var wire 8 " in2 [7:0] $end
$var wire 8 # in3 [7:0] $end
$var wire 8 $ in4 [7:0] $end
$var wire 2 % enbl [1:0] $end
$var wire 1 & clk $end
$var wire 1 ' rst $end
$var reg 8 ( out [7:0] $end
$var wire 8 ) out1 [7:0] $end
$var wire 8 * out2 [7:0] $end
$var wire 8 + sum [7:0] $end
$var reg 8 , a [7:0] $end
$var reg 8 - b [7:0] $end
$var reg 8 . c [7:0] $end
$var reg 8 / d [7:0] $end
$var reg 8 0 sum1 [7:0] $end
$var reg 8 1 sum2 [7:0] $end
$upscope $end

$upscope $end

$enddefinitions $end

#0
$dumpvars
0&
1'
bxxxxxxxx ,
bxxxxxxxx -
bxxxxxxxx .
bxxxxxxxx /
bxx %
bxxxxxxxx !
bxxxxxxxx "
bxxxxxxxx #
bxxxxxxxx $
bxxxxxxxx (
bxxxxxxxx )
bxxxxxxxx *
bxxxxxxxx +
bxxxxxxxx 0
bxxxxxxxx 1
$end
#10
1&
b00000000 ,
b00000000 )
b00000000 -
b00000000 .
b00000000 *
b00000000 /
b00000000 +
b00000000 (
b00000000 0
b00000000 1
#20
0&
0'
b00 %
b00000010 !
b00000011 "
b00000100 #
b00000101 $
b00000010 ,
b00000101 )
b00000011 -
#30
1&
#40
0&
b01 %
#50
1&
b00000100 .
b00001001 *
b00000101 0
#60
0&
b10 %
#70
1&
b00000101 /
b00001110 +
b00001001 1
#80
0&
#90
1&
b00001110 (
